<?xml version="1.0" encoding="UTF-8"?>
<persistence xmlns="http://xmlns.jcp.org/xml/ns/persistence" version="2.1">

    <persistence-unit name="jee-test-pu" transaction-type="JTA">
        <provider>org.hibernate.jpa.HibernatePersistenceProvider</provider>
        <jta-data-source>java:jboss/datasources/ExampleDS</jta-data-source>
        <properties>
            <property name="javax.persistence.schema-generation.database.action" value="create"/>
        </properties>
    </persistence-unit>
</persistence>
